django_smart_pagination-1.0.1.dist-info/DESCRIPTION.rst
django_smart_pagination-1.0.1.dist-info/METADATA
django_smart_pagination-1.0.1.dist-info/RECORD
django_smart_pagination-1.0.1.dist-info/WHEEL
django_smart_pagination-1.0.1.dist-info/metadata.json
django_smart_pagination-1.0.1.dist-info/top_level.txt
smart_pagination/__init__.py
smart_pagination/error_messages.py
smart_pagination/pagination.py
smart_pagination/templatetags/__init__.py
smart_pagination/templatetags/pagination_jinja.py
smart_pagination/templatetags/pagination_tags.py
