Metadata-Version: 2.0
Name: django-smart-pagination
Version: 1.0.1
Summary: Generate pagination links in Django Templates
Home-page: https://github.com/livioribeiro/django-smart-pagination
Author: Livio Ribeiro
Author-email: livioribeiro@outlook.com
License: BSD
Keywords: django pagination page links
Platform: UNKNOWN
Classifier: Development Status :: 4 - Beta
Classifier: Environment :: Web Environment
Classifier: Framework :: Django
Classifier: Intended Audience :: Developers
Classifier: License :: OSI Approved :: BSD License
Classifier: Operating System :: OS Independent
Classifier: Programming Language :: Python
Classifier: Programming Language :: Python :: 3
Classifier: Programming Language :: Python :: 3.3
Classifier: Programming Language :: Python :: 3.4
Classifier: Programming Language :: Python :: 3.5
Classifier: Topic :: Internet :: WWW/HTTP
Classifier: Topic :: Internet :: WWW/HTTP :: Dynamic Content
Requires-Dist: Django
Provides-Extra: test
Requires-Dist: Jinja2; extra == 'test'
Requires-Dist: pytest; extra == 'test'
Requires-Dist: pytest-cov; extra == 'test'
Requires-Dist: pytest-django; extra == 'test'
